embedsim/__init__.py
embedsim/backends.py
embedsim/embedsim.py
embedsim-0.1.0.dist-info/licenses/LICENSE
embedsim-0.1.0.dist-info/METADATA
embedsim-0.1.0.dist-info/WHEEL
embedsim-0.1.0.dist-info/top_level.txt
embedsim-0.1.0.dist-info/RECORD
