Metadata-Version: 2.4
Name: embedsim
Version: 0.1.0
Summary: A Python library for computing Embedding Similarity scores using embeddings
Author-email: Agent CI <hello@agentci.com>, Travis Dent <root@a10k.co>
License-Expression: MIT
Project-URL: Homepage, https://github.com/Agent-CI/embedsim
Project-URL: Repository, https://github.com/Agent-CI/embedsim.git
Project-URL: Issues, https://github.com/Agent-CI/embedsim/issues
Keywords: embeddings,similarity,machine-learning,nlp,vector-similarity
Classifier: Development Status :: 3 - Alpha
Classifier: Intended Audience :: Developers
Classifier: Operating System :: OS Independent
Classifier: Programming Language :: Python :: 3
Classifier: Programming Language :: Python :: 3.10
Classifier: Programming Language :: Python :: 3.11
Classifier: Programming Language :: Python :: 3.12
Classifier: Topic :: Scientific/Engineering :: Artificial Intelligence
Classifier: Topic :: Software Development :: Libraries :: Python Modules
Requires-Python: >=3.10
License-File: LICENSE
Requires-Dist: numpy>=1.21.0
Provides-Extra: openai
Requires-Dist: openai>=1.0.0; extra == "openai"
Provides-Extra: sentence-transformers
Requires-Dist: sentence-transformers>=2.2.0; extra == "sentence-transformers"
Provides-Extra: dev
Requires-Dist: pytest>=7.0; extra == "dev"
Requires-Dist: pytest-cov; extra == "dev"
Requires-Dist: mypy; extra == "dev"
Requires-Dist: python-dotenv>=1.0.0; extra == "dev"
Dynamic: license-file
